y4d/__init__.py
y4d/checkAPI.py
y4d/codeParser.py
y4d/commentController.py
y4d/isolator.py
y4d/restrictor.py
y4d-1.0.0.dist-info/entry_points.txt
y4d-1.0.0.dist-info/METADATA
y4d-1.0.0.dist-info/WHEEL
y4d-1.0.0.dist-info/RECORD
