Metadata-Version: 2.1
Name: y4d
Version: 1.0.0
Summary: 
Author: BahouA
Author-email: antonbahou@gmail.com
Requires-Python: >=3.6,<4.0
Classifier: Programming Language :: Python :: 3
Classifier: Programming Language :: Python :: 3.6
Classifier: Programming Language :: Python :: 3.7
Classifier: Programming Language :: Python :: 3.8
Classifier: Programming Language :: Python :: 3.9
Classifier: Programming Language :: Python :: 3.10
Classifier: Programming Language :: Python :: 3.11
Requires-Dist: libclang[all] (>=16.0.0,<17.0.0)
Requires-Dist: pyyaml[all] (>=6.0,<7.0)
Requires-Dist: typer[all] (>=0.9.0,<0.10.0)
